wordle_cheater/__init__.py
wordle_cheater/cheater.py
wordle_cheater/cli.py
wordle_cheater/dictionary.py
wordle_cheater/interface.py
wordle_cheater/interface_base.py
wordle_cheater-0.3.1.dist-info/entry_points.txt
wordle_cheater-0.3.1.dist-info/LICENSE
wordle_cheater-0.3.1.dist-info/WHEEL
wordle_cheater-0.3.1.dist-info/METADATA
wordle_cheater-0.3.1.dist-info/RECORD
