Metadata-Version: 2.1
Name: wordle-cheater
Version: 0.3.1
Summary: Utilities for cheating on Wordle :(
Home-page: https://github.com/edsq/wordle-cheater
License: MIT
Author: Edward Eskew
Author-email: eeskew@gatech.edu
Requires-Python: >=3.7,<4.0
Classifier: License :: OSI Approved :: MIT License
Classifier: Programming Language :: Python :: 3
Classifier: Programming Language :: Python :: 3.10
Classifier: Programming Language :: Python :: 3.7
Classifier: Programming Language :: Python :: 3.8
Classifier: Programming Language :: Python :: 3.9
Requires-Dist: click (>=8.0.4,<9.0.0)
Requires-Dist: importlib-metadata (>=4.2,<5.0); python_version < "3.8"
Project-URL: Documentation, http://wordle-cheater.readthedocs.io/
Project-URL: Repository, https://github.com/edsq/wordle-cheater
